relmgr/__init__.py
relmgr/_caching.py
relmgr/_core.py
relmgr/_enforcing.py
relmgr/_persist_support.py
relmgr/relationship_manager.py
relmgr/__pycache__/__init__.cpython-38.pyc
relmgr/__pycache__/relationship_manager.cpython-38.pyc
rm_python/__init__.py
rm_python/relationship_manager.py
relationship_manager-2.0.1.dist-info/METADATA
relationship_manager-2.0.1.dist-info/WHEEL
relationship_manager-2.0.1.dist-info/top_level.txt
relationship_manager-2.0.1.dist-info/RECORD
