Metadata-Version: 2.1
Name: relationship-manager
Version: 2.0.1
Summary: Lightweight Object Database, manages relationships between classes
Home-page: https://github.com/abulka/relationship-manager
Author: Andy Bulka
Author-email: abulka@gmail.com
License: MIT
Platform: UNKNOWN
Classifier: License :: OSI Approved :: MIT License
Classifier: Programming Language :: Python :: 3
Classifier: Programming Language :: Python :: 3.8
